django_error_report-0.2.0.dist-info/DESCRIPTION.rst
django_error_report-0.2.0.dist-info/METADATA
django_error_report-0.2.0.dist-info/RECORD
django_error_report-0.2.0.dist-info/WHEEL
django_error_report-0.2.0.dist-info/metadata.json
django_error_report-0.2.0.dist-info/top_level.txt
error_report/__init__.py
error_report/admin.py
error_report/apps.py
error_report/middleware.py
error_report/models.py
error_report/settings.py
error_report/urls.py
error_report/views.py
error_report/migrations/0001_initial.py
error_report/migrations/__init__.py
