Metadata-Version: 2.0
Name: django-error-report
Version: 0.2.0
Summary: View Django Error Report in Django Admin
Home-page: https://github.com/mhsiddiqui/django-error-report
Author: M Hassan Siddiqui
Author-email: mhassan.eeng@gmail.com
License: BSD License
Platform: UNKNOWN
Classifier: Environment :: Web Environment
Classifier: Intended Audience :: Developers
Classifier: License :: OSI Approved :: BSD License
Classifier: Operating System :: OS Independent
Classifier: Programming Language :: Python
Classifier: Framework :: Django
Requires-Dist: Django (>=1.7)
